scrapy_swarm/__init__.py
scrapy_swarm/cmdline.py
scrapy_swarm/connection.py
scrapy_swarm/defaults.py
scrapy_swarm/dupefilter.py
scrapy_swarm/middlewares.py
scrapy_swarm/nsq.py
scrapy_swarm/picklecompat.py
scrapy_swarm/pipelines.py
scrapy_swarm/queue.py
scrapy_swarm/scheduler.py
scrapy_swarm/spiders.py
scrapy_swarm/stats.py
scrapy_swarm/utils.py
scrapy_swarm/commonds/__init__.py
scrapy_swarm-0.0.24.dist-info/METADATA
scrapy_swarm-0.0.24.dist-info/WHEEL
scrapy_swarm-0.0.24.dist-info/entry_points.txt
scrapy_swarm-0.0.24.dist-info/top_level.txt
scrapy_swarm-0.0.24.dist-info/RECORD
